Redistr-0.0b9.dist-info/DESCRIPTION.rst
Redistr-0.0b9.dist-info/METADATA
Redistr-0.0b9.dist-info/RECORD
Redistr-0.0b9.dist-info/WHEEL
Redistr-0.0b9.dist-info/metadata.json
Redistr-0.0b9.dist-info/top_level.txt
redistr/BaseStructure.py
redistr/Dict.py
redistr/HyperLogLog.py
redistr/List.py
redistr/Queue.py
redistr/Set.py
redistr/__init__.py
redistr/__main__.py
