Metadata-Version: 2.0
Name: Redistr
Version: 0.0b9
Summary: Redis backed Python data structure interface.
Home-page: https://www.github.com/copyrighthero/Redistr
Author: Hansheng Zhao
Author-email: copyrighthero@gmail.com
License: BSD-2-Clause + MIT
Download-URL: https://www.github.com/copyrighthero/Redistr
Project-URL: Source, https://www.github.com/copyrighthero/Redistr
Keywords: Redis Remote Data-structure Multi-processing
Platform: UNKNOWN
Classifier: Development Status :: 4 - Beta
Classifier: License :: OSI Approved :: BSD License
Classifier: License :: OSI Approved :: MIT License
Classifier: Natural Language :: English
Classifier: Operating System :: OS Independent
Classifier: Programming Language :: Python :: 3 :: Only
Requires-Dist: msgpack-python
Requires-Dist: redis
Requires-Dist: seco
